kong_config_builder/__init__.py
kong_config_builder/base.py
kong_config_builder/consumer.py
kong_config_builder/plugin.py
kong_config_builder/service.py
kong_config_builder/upstream.py
kong_config_builder/utils.py
kong_config_builder-0.0.1.dist-info/LICENSE
kong_config_builder-0.0.1.dist-info/METADATA
kong_config_builder-0.0.1.dist-info/WHEEL
kong_config_builder-0.0.1.dist-info/top_level.txt
kong_config_builder-0.0.1.dist-info/RECORD
