Metadata-Version: 2.1
Name: kong-config-builder
Version: 0.0.1
Summary: Kong declarative configuration builder
Home-page: https://github.com/olxbr/kong-config-builder/
Author: Olx
License: MIT
Download-URL: https://github.com/olxbr/kong-config-builder/archive/master.zip
Platform: UNKNOWN
Classifier: Programming Language :: Python :: 3
Classifier: License :: OSI Approved :: Apache Software License
Classifier: Topic :: Software Development :: Libraries :: Python Modules
Classifier: Topic :: Software Development :: Libraries :: Application Frameworks
Requires-Dist: pyyaml (==5.3.1)
